Workbook

Sheet Instrucciones
A1: Cotización – Fase 1: medición de gas y quemador piloto (máquina 1)
A3: Para qué es este archivo
A4: Lista de equipos para cotizar con distribuidores en Guatemala, con un precio de referencia de EE. UU. y un estimado puesto en Guatemala.
A6: Qué celdas llenar
A7: • Celdas AMARILLAS en la hoja 'Fase 1': precios que te den los proveedores en Guatemala (Q por unidad), nombre del proveedor y tiempo de entrega.
A8: • Texto AZUL en la hoja 'Supuestos': tipo de cambio, flete, DAI e IVA. Al cambiarlos se recalcula el estimado.
A10: Cómo leer las columnas
A11: • 'Precio ref. EE. UU.': precio encontrado en internet en octubre de 2026 (link en 'Fuente del precio'). Es solo referencia; puede haber cambiado.
A12: • 'Amazon EE. UU.': link de búsqueda en Amazon con la especificación. Revisa vendedor, garantía y si envía a Guatemala.
A13: • 'Estimado puesto en GT': precio EE. UU. × (1 + flete) × (1 + DAI) × (1 + IVA) × tipo de cambio. NO es una cotización: sirve para comparar.
A14: • Si una fila no tiene precio de referencia, es porque no se encontró uno confiable: hay que cotizarla directamente.
A16: Recomendaciones para cotizar
... A20: • Pregunta a tu proveedor de gas LP si instala telemetría de nivel en el tanque (muchos lo hacen para programar entregas).

Sheet Supuestos
A1: Supuestos para el estimado puesto en Guatemala
A3: Concepto | B3: Valor | C3: Nota / fuente
A4: Tipo de cambio (Q por USD) | B4: 7.7 | C4: Supuesto: valor aproximado. Actualizar con el tipo de cambio de referencia del Banco de Guatemala (banguat.gob.gt).
A5: Flete / courier / seguro (% del precio) | B5: 0.15 | C5: Supuesto: depende del peso y del courier. Pedir cotización de envío.
A6: DAI – derecho arancelario (%) | B6: 0.05 | C6: Supuesto: varía por partida arancelaria (equipo industrial suele ser 0–15 %). Confirmar con un agente aduanal.
A7: IVA Guatemala (%) | B7: 0.12 | C7: IVA general de Guatemala: 12 %.
A9: Factor total sobre el precio de EE. UU. (en USD) | B9: =(1+B5)*(1+B6)*(1+B7) -> 1.3524

Sheet Fase 1
A1: Fase 1 – Medición de gas (máquina 1) y quemador piloto con control
A3: # | B3: Categoría | C3: Equipo | D3: Especificación para cotizar | E3: Cant. | F3: Unidad | G3: Modelo de referencia | H3: Precio ref. EE. UU. (USD c/u) | I3: Fuente del precio | J3: Amazon EE. UU. | K3: Subtotal EE. UU. (USD) | L3: Estimado puesto en GT (Q c/u) | M3: Subtotal estimado GT (Q) | N3: Cotización GT 1 (Q c/u) | O3: Proveedor 1 | P3: Cotización GT 2 (Q c/u) | Q3: Proveedor 2 | R3: Tiempo de entrega | S3: Notas
A4: Medición de gas LP
A5: 1 | B5: Gas | C5: Medidor de gas LP por máquina | D5: Medidor para GLP en fase VAPOR, línea de 1/2", presión de trabajo 20 psi (máx. ≥ 25 psi), salida de pulsos o Modbus RS-485, calibrado para mezcla propano/butano. Indicar caudal máximo de la máquina (BTU/h o gal/h). | E5: 1 | F5: pza | G5: Siargo serie MF-GD (GLP) / medidor rotativo | I5: Siargo MF-GD (catálogo, sin precio) | J5: Buscar en Amazon | K5: =IF(H5="","",H5*E5) | L5: =IF(H5="","",H5*Supuestos!$B$9*Supuestos!$B$4) | M5: =IF(L5="","",L5*E5) | S5: Muchos medidores de diafragma (ej. AC-250) son solo hasta 5–10 psi: no sirven a 20 psi. Dimensionar con el consumo real.
A6: 2 | B6: Gas | C6: Transmisor de presión de gas | D6: 0–30 psi manométrico, salida 4–20 mA a 2 hilos, partes en contacto acero inox. 316L, apto para GLP, conexión 1/4" o 1/2" NPT. | E6: 1 | F6: pza | G6: L-com PT989-30PV1E22B1C10G | H6: 107.99 | I6: L-com | J6: Buscar en Amazon | K6: =IF(H6="","",H6*E6) -> 107.99 | L6: =IF(H6="","",H6*Supuestos!$B$9*Supuestos!$B$4) -> 1124.5517 | M6: =IF(L6="","",L6*E6) -> 1124.5517 | S6: Opción de mayor precisión: Omega PX359-030GI (~USD 409). Confirmar compatibilidad de sellos con GLP.
A7: 3 | B7: Gas | C7: Nivel del tanque estacionario (para pedidos) | D7: Lectura de nivel del tanque de GLP con salida 4–20 mA o telemetría. | E7: 1 | F7: servicio | G7: Rochester R3D + transmisor / telemetría del proveedor | I7: Rochester R3D (salida en voltaje) | J7: Buscar en Amazon | K7: =IF(H7="","",H7*E7) | L7: =IF(H7="","",H7*Supuestos!$B$9*Supuestos!$B$4) | M7: =IF(L7="","",L7*E7) | S7: Preguntar primero al proveedor de gas LP: muchos instalan telemetría sin costo para programar entregas.
A8: Temperatura
A9: 4 | B9: Temperatura | C9: Sensor PT100 con cabezal | D9: RTD PT100 clase A o B, 3 hilos, vaina inox. 316, rosca 1/2" NPT, cabezal industrial. Indicar longitud de inserción y rango (0–150 °C). | E9: 6 | F9: pza | G9: Omega PR-14 (PT100, 1/2" NPT) | H9: 96.08 | I9: Omega | J9: Buscar en Amazon | K9: =IF(H9="","",H9*E9) -> 576.48 | L9: =IF(H9="","",H9*Supuestos!$B$9*Supuestos!$B$4) -> 1000.5272 | M9: =IF(L9="","",L9*E9) -> 6003.163 | S9: 6 = 4 zonas de quemadores + tina de látex + tina de coagulante. Ya tienes 1 transmisor 0–150 °C.
A10: 5 | B10: Temperatura | C10: Termopozo | D10: Termopozo inox. 316 para el sensor anterior, 1/2" NPT, longitud según tina/zona. | E10: 6 | F10: pza | G10: Según fabricante del sensor | I10: Cotizar con el sensor | J10: Buscar en Amazon | K10: =IF(H10="","",H10*E10) | L10: =IF(H10="","",H10*Supuestos!$B$9*Supuestos!$B$4) | M10: =IF(L10="","",L10*E10) | S10: Permite sacar el sensor sin vaciar la tina.
A11: 6 | B11: Temperatura | C11: Módulo de entradas PT100 (directo) | D11: Módulo de expansión para PLC con 4 entradas RTD PT100 directas (sin transmisor). | E11: 2 | F11: pza | G11: Schneider TM3TI4 | H11: 334.11 | I11: Standard Electric Supply | J11: Buscar en Amazon | K11: =IF(H11="","",H11*E11) -> 668.22 | L11: =IF(H11="","",H11*Supuestos!$B$9*Supuestos!$B$4) -> 3479.2478 | M11: =IF(L11="","",L11*E11) -> 6958.4956 | S11: Con este módulo no se compran transmisores PT100 → 4–20 mA. Si se cambia a Siemens: SM 1231 RTD.
A12: PLC y señales
A13: 7 | B13: PLC | C13: Módulo de entradas 4–20 mA | D13: Módulo de expansión con 4 entradas analógicas 4–20 mA, 12 bits. | E13: 1 | F13: pza | G13: Schneider TM3AI4 | H13: 278.23 | I13: Standard Electric Supply | J13: Buscar en Amazon | K13: =IF(H13="","",H13*E13) -> 278.23 | L13: =IF(H13="","",H13*Supuestos!$B$9*Supuestos!$B$4) -> 2897.3425 | M13: =IF(L13="","",L13*E13) -> 2897.3425 | S13: Para feedback de válvula, presión de gas y futuros sensores, sin resistencias. Otra ref.: Powermatic USD 219.
A14: 8 | B14: PLC | C14: Resistencias de precisión 499 Ω | D14: Resistencia 499 Ω, tolerancia 0.1 % (o 1 %), ½ W, para leer 4–20 mA en entradas 0–10 V. | E14: 4 | F14: pza | G14: Resistencia metal film 499 Ω 0.1 % | I14: No se encontró precio confiable | J14: Buscar en Amazon | K14: =IF(H14="","",H14*E14) | L14: =IF(H14="","",H14*Supuestos!$B$9*Supuestos!$B$4) | M14: =IF(L14="","",L14*E14) | S14: Solo si NO se compra el TM3AI4. Son de muy bajo costo; pedir unas de repuesto.
A15: Seguridad del quemador piloto
A16: 9 | B16: Seguridad | C16: Relé de control de llama | D16: Programador / relé de supervisión de llama compatible con el quemador (atmosférico, GLP). Debe cerrar la solenoide ante pérdida de llama. | E16: 1 | F16: pza | G16: Honeywell RM7890 (+ base y amplificador) | H16: 1190.11 | I16: Kele | J16: Buscar en Amazon | K16: =IF(H16="","",H16*E16) -> 1190.11 | L16: =IF(H16="","",H16*Supuestos!$B$9*Supuestos!$B$4) -> 12393.187 | M16: =IF(L16="","",L16*E16) -> 12393.187 | S16: Requiere base de montaje y amplificador aparte. Lo debe definir el técnico de quemadores: para quemadores pequeños hay relés de ionización más económicos.
A17: 10 | B17: Seguridad | C17: Sensor de llama | D17: Detector UV o varilla de ionización compatible con el relé anterior. | E17: 1 | F17: pza | G17: Fireye UV7R4 (UV, 1/2" NPT) | H17: 215.14 | I17: Jackson Systems | J17: Buscar en Amazon | K17: =IF(H17="","",H17*E17) -> 215.14 | L17: =IF(H17="","",H17*Supuestos!$B$9*Supuestos!$B$4) -> 2240.3561 | M17: =IF(L17="","",L17*E17) -> 2240.3561 | S17: Debe ser compatible con el relé elegido.
A18: 11 | B18: Seguridad | C18: Válvula de control para gas (réplica) | D18: Válvula de bola característica (V-port) o válvula modulante de gas, 1/2", apta para GLP, con actuador 4–20 mA y feedback. | E18: 0 | F18: pza | G18: Assured Automation S4 + válvula (ya tienes 1) | I18: Cotizar con Assured Automation / distribuidor | J18: Buscar en Amazon | K18: =IF(H18="","",H18*E18) | L18: =IF(H18="","",H18*Supuestos!$B$9*Supuestos!$B$4) | M18: =IF(L18="","",L18*E18) | S18: Cantidad 0 en fase 1: el piloto usa la S4 que ya tienes. Para réplica: 4 por máquina.
A19: Tablero y red
A20: 12 | B20: Tablero | C20: Fuente 24 VDC | D20: Fuente conmutada riel DIN, 24 VDC, 5 A (120 W), entrada 120/240 VAC. | E20: 1 | F20: pza | G20: Mean Well NDR-120-24 | I20: Precios encontrados solo en otras monedas | J20: Buscar en Amazon | K20: =IF(H20="","",H20*E20) | L20: =IF(H20="","",H20*Supuestos!$B$9*Supuestos!$B$4) | M20: =IF(L20="","",L20*E20) | S20: Ya tienes una fuente de 24 V; esta sería para el tablero de la máquina 1.
A21: 13 | B21: Tablero | C21: Gabinete | D21: Gabinete metálico NEMA 4 / IP65 aprox. 16×12×6" (400×300×150 mm) con doble fondo. | E21: 1 | F21: pza | G21: Hoffman A16H1206SSLP (inox.) | H21: 1642.16 | I21: Kele | J21: Buscar en Amazon | K21: =IF(H21="","",H21*E21) -> 1642.16 | L21: =IF(H21="","",H21*Supuestos!$B$9*Supuestos!$B$4) -> 17100.6 | M21: =IF(L21="","",L21*E21) -> 17100.6 | S21: Referencia ALTA (acero inoxidable). Uno de acero al carbón pintado, fabricado o comprado en Guatemala, cuesta mucho menos.
A22: 14 | B22: Tablero | C22: Cable de señal blindado | D22: Cable 1 par trenzado 18 AWG con blindaje y drenaje (tipo Belden 8760), rollo de 250 ft. | E22: 1 | F22: rollo | G22: Belden 8760 (250 ft) | H22: 409 | I22: Markertek | J22: Buscar en Amazon | K22: =IF(H22="","",H22*E22) -> 409 | L22: =IF(H22="","",H22*Supuestos!$B$9*Supuestos!$B$4) -> 4259.1133 | M22: =IF(L22="","",L22*E22) -> 4259.1133 | S22: ≈ USD 1.64/ft. Equivalentes locales sirven si son par trenzado con blindaje.
A23: 15 | B23: Tablero | C23: Material eléctrico menor | D23: Breakers/fusibles, borneras con puente, relés de interfaz, canaleta, riel DIN, punteras, prensaestopas, etiquetas. | E23: 1 | F23: lote | G23: Varios | I23: Cotizar localmente | J23: Buscar en Amazon | K23: =IF(H23="","",H23*E23) | L23: =IF(H23="","",H23*Supuestos!$B$9*Supuestos!$B$4) | M23: =IF(L23="","",L23*E23) | S23: Conviene comprarlo localmente.
A24: 16 | B24: Red | C24: Switch Ethernet industrial | D24: Switch no administrable, 5 puertos RJ45, riel DIN, alimentación 24 VDC. | E24: 1 | F24: pza | G24: AutomationDirect STRIDE SE2-SW5UG-T | H24: 276.5 | I24: AutomationDirect | J24: Buscar en Amazon | K24: =IF(H24="","",H24*E24) -> 276.5 | L24: =IF(H24="","",H24*Supuestos!$B$9*Supuestos!$B$4) -> 2879.3272 | M24: =IF(L24="","",L24*E24) -> 2879.3272 | S24: Para unir PLC(s) y servidor en la red de control.
A25: 17 | B25: Red | C25: Servidor (colector + base de datos + Grafana) | D25: Mini PC sin ventilador o PC de escritorio siempre encendida: 8 GB RAM, SSD 256 GB, Ethernet. O máquina virtual de TI. | E25: 1 | F25: pza | G25: Mini PC industrial / VM de TI | I25: Cotizar con TI | J25: Buscar en Amazon | K25: =IF(H25="","",H25*E25) | L25: =IF(H25="","",H25*Supuestos!$B$9*Supuestos!$B$4) | M25: =IF(L25="","",L25*E25) | S25: Si TI da una máquina virtual, esta fila queda en 0.
A26: Servicios
A27: 18 | B27: Servicios | C27: Instalación de gas y prueba de hermeticidad | D27: Instalador de gas autorizado: montaje del medidor y transmisor de presión, prueba de fugas, revisión del tren de gas del quemador piloto. | E27: 1 | F27: servicio | G27: Instalador autorizado local | I27: Cotizar localmente | K27: =IF(H27="","",H27*E27) | L27: =IF(H27="","",H27*Supuestos!$B$9*Supuestos!$B$4) | M27: =IF(L27="","",L27*E27) | S27: Obligatorio por seguridad.
A28: 19 | B28: Servicios | C28: Técnico de quemadores | D28: Selección e instalación de la detección de llama, ajuste de fuego mínimo de la válvula modulante en el quemador piloto. | E28: 1 | F28: servicio | G28: Técnico de combustión local | I28: Cotizar localmente | K28: =IF(H28="","",H28*E28) | L28: =IF(H28="","",H28*Supuestos!$B$9*Supuestos!$B$4) | M28: =IF(L28="","",L28*E28) | S28: Define el relé y el sensor de llama correctos.
A30: Ejemplo de cómo llenar las celdas amarillas:
C31: (fila de ejemplo, no suma) | N31: 2450 | O31: Distribuidor X | P31: 2600 | Q31: Distribuidor Y | R31: 3 semanas
J33: TOTALES | K33: =SUM(K4:K28) -> 5363.83 | M33: =SUM(M4:M28) -> 55856.136 | N33: =SUMPRODUCT(N4:N28,E4:E28) -> 0 | P33: =SUMPRODUCT(P4:P28,E4:E28) -> 0
J34: Nota | K34: Los totales de referencia solo suman las filas que tienen precio de EE. UU.; las filas sin precio (medidor de gas, servicios, etc.) hay que cotizarlas y pueden ser una parte importante del total.
K35: Totales de cotización GT = precio unitario × cantidad.

Sheet Referencia PLC
A1: Referencia de plataformas de PLC (para decidir la marca de la planta)
A3: Equipo | B3: Modelo | C3: Precio ref. EE. UU. (USD) | D3: Fuente | E3: Estimado puesto en GT (Q) | F3: Notas
A4: Schneider M221 (el que ya tienes) | B4: TM221ME16R | C4: 309 | D4: Powermatic | E4: =C4*Supuestos!$B$9*Supuestos!$B$4 -> 3217.7653 | F4: Software gratis (Machine Expert Basic). Solo Ladder/IL. 2 entradas 0–10 V integradas.
A5: Schneider salida analógica ×4 | B5: TM3AQ4 | C5: 334.11 | D5: Standard Electric Supply | E5: =C5*Supuestos!$B$9*Supuestos!$B$4 -> 3479.2478 | F5: Para los 4 quemadores de una máquina (réplica).
A6: Siemens S7-1200 | B6: CPU 1214C DC/DC/DC (6ES7214-1AG40-0XB0) | C6: 320 | D6: eBay (revendedor) | E6: =C6*Supuestos!$B$9*Supuestos!$B$4 -> 3332.3136 | F6: Precio de revendedor; en Farnell Irlanda ~EUR 414. Software TIA Portal es de paga. Ladder + SCL (texto estructurado).
A7: Siemens LOGO! 8 (lo que tienen las máquinas) | B7: 6ED1052-1MD08-0BA1 | C7: 163.77 | D7: Automation Warehouse | E7: =C7*Supuestos!$B$9*Supuestos!$B$4 -> 1705.4156 | F7: Relé programable: sirve para secuencias simples, no para 4 lazos PID con supervisión.
A9: Precios de referencia encontrados en internet en octubre de 2026; pedir cotización a distribuidores autorizados en Guatemala.
